ezclai/__init__.py
ezclai/api.py
ezclai/behavior_context.py
ezclai/main.py
ezclai/message_creation.py
ezclai/ocr_drivers/__init__.py
ezclai/ocr_drivers/base_driver.py
ezclai/ocr_drivers/linux_driver.py
ezclai-0.3.1.dist-info/METADATA
ezclai-0.3.1.dist-info/WHEEL
ezclai-0.3.1.dist-info/entry_points.txt
ezclai-0.3.1.dist-info/RECORD
