Metadata-Version: 2.1
Name: ezclai
Version: 0.3.1
Summary: Command Line AI- this tool lets you call ChatGPT from a CLI
License: Proprietary
Author: apockill
Author-email: apocthiel@gmail.com
Requires-Python: >=3.8,<4.0
Classifier: License :: Other/Proprietary License
Classifier: Programming Language :: Python :: 3
Classifier: Programming Language :: Python :: 3.8
Classifier: Programming Language :: Python :: 3.9
Classifier: Programming Language :: Python :: 3.10
Classifier: Programming Language :: Python :: 3.11
Requires-Dist: PyAutoGUI (>=0.9.53,<0.10.0)
Requires-Dist: PyWinCtl (>=0.0.43,<0.0.44)
Requires-Dist: clipboard (>=0.0.4,<0.0.5)
Requires-Dist: openai (>=0.27.0,<0.28.0)
Requires-Dist: pytesseract (>=0.3.10,<0.4.0)
